pytest_kuunda/__init__.py
pytest_kuunda/plugin.py
pytest_kuunda-0.1.0.dist-info/LICENSE
pytest_kuunda-0.1.0.dist-info/METADATA
pytest_kuunda-0.1.0.dist-info/WHEEL
pytest_kuunda-0.1.0.dist-info/entry_points.txt
pytest_kuunda-0.1.0.dist-info/top_level.txt
pytest_kuunda-0.1.0.dist-info/RECORD
