Metadata-Version: 2.1
Name: pytest-kuunda
Version: 0.1.0
Summary: pytest plugin to help with test data setup for PySpark tests
Author-email: Sven Hofstede <info@svenhofstede.com>
Maintainer-email: Sven Hofstede <info@svenhofstede.com>
License: 
Project-URL: Repository, https://github.com/svenhofstede/pytest-kuunda
Project-URL: Homepage, https://github.com/svenhofstede/pytest-kuunda
Classifier: Framework :: Pytest
Classifier: Development Status :: 4 - Beta
Classifier: Intended Audience :: Developers
Classifier: Topic :: Software Development :: Testing
Classifier: Operating System :: OS Independent
Classifier: Programming Language :: Python
Classifier: Programming Language :: Python :: 3.8
Classifier: Programming Language :: Python :: 3.9
Classifier: Programming Language :: Python :: 3.10
Classifier: Programming Language :: Python :: 3.11
Classifier: Programming Language :: Python :: 3.12
Classifier: Programming Language :: Python :: 3 :: Only
Classifier: Programming Language :: Python :: Implementation :: CPython
Classifier: Programming Language :: Python :: Implementation :: PyPy
Classifier: License :: OSI Approved :: MIT License
Requires-Python: >=3.8
License-File: LICENSE
Requires-Dist: pytest >=6.2.0
Requires-Dist: pyspark >=3
Provides-Extra: delta
Requires-Dist: delta-spark ; extra == 'delta'
